afc_imbalanced_learning/__init__.py
afc_imbalanced_learning/afc.py
afc_imbalanced_learning/conformal_transformation.py
afc_imbalanced_learning/distance.py
afc_imbalanced_learning/kernel.py
afc_imbalanced_learning/metrics.py
afc_svm_imbalanced_learning-0.10.0.dist-info/LICENSE
afc_svm_imbalanced_learning-0.10.0.dist-info/METADATA
afc_svm_imbalanced_learning-0.10.0.dist-info/WHEEL
afc_svm_imbalanced_learning-0.10.0.dist-info/top_level.txt
afc_svm_imbalanced_learning-0.10.0.dist-info/RECORD
